README.txt
setup.cfg
setup.py
anobii/__init__.py
anobii.api.egg-info/PKG-INFO
anobii.api.egg-info/SOURCES.txt
anobii.api.egg-info/dependency_links.txt
anobii.api.egg-info/entry_points.txt
anobii.api.egg-info/namespace_packages.txt
anobii.api.egg-info/not-zip-safe
anobii.api.egg-info/requires.txt
anobii.api.egg-info/top_level.txt
anobii/api/__init__.py
anobii/api/cache.py
anobii/api/exceptions.py
anobii/api/tokencache.py
anobii/api/xmlnode.py
anobii/api/tests/test_anobiiapi.py
docs/HISTORY.txt