Metadata-Version: 1.0
Name: anobii.api
Version: 0.1dev-r11
Summary: wrapper for Anobii API
Home-page: http://code.google.com/p/anobiiapi/
Author: Massimo Azzolini
Author-email: massimo.azzolini@gmail.com
License: GPL
Keywords: anobii api python
Platform: UNKNOWN
Classifier: Programming Language :: Python
Classifier: Topic :: Software Development :: Libraries :: Python Modules
